setup.py
rev0001q1.egg-info/PKG-INFO
rev0001q1.egg-info/SOURCES.txt
rev0001q1.egg-info/dependency_links.txt
rev0001q1.egg-info/top_level.txt
empty_pkg/__init__.py
