Metadata-Version: 2.0
Name: rev0001q1
Version: 2.0.0
Summary: This is a reverse shell, if you find this in your system consider it compromised
Home-page: UNKNOWN
Author: isHaacK
Author-email: UNKNOWN
License: UNKNOWN
Platform: UNKNOWN
